{
  "records": [
    {
      "fields": {
        "名称": [
          {
            "text": "小红书_2026-02",
            "type": "text"
          }
        ],
        "实际消费": 776237.854545455,
        "当前有效线索成本": 4593.12339967725,
        "月份": "2026-02",
        "有效线索": 169,
        "渠道": "小红书",
        "线索成本": 1826.44201069519,
        "线索数": 425
      },
      "id": "recvenjNgqgN4p",
      "record_id": "recvenjNgqgN4p"
    },
    {
      "fields": {
        "名称": [
          {
            "text": "朋友圈_2026-02",
            "type": "text"
          }
        ],
        "实际消费": 989745.243781095,
        "当前有效线索成本": 2653.47250343457,
        "月份": "2026-02",
        "有效线索": 373,
        "渠道": "朋友圈",
        "线索成本": 746.977542476298,
        "线索数": 1325
      },
      "id": "recvenIsDKmmVQ",
      "record_id": "recvenIsDKmmVQ"
    },
    {
      "fields": {
        "名称": [
          {
            "text": "抖音私信_2026-02",
            "type": "text"
          }
        ],
        "实际消费": 1191360.16744186,
        "当前有效线索成本": 2751.40916268328,
        "月份": "2026-02",
        "有效线索": 433,
        "渠道": "抖音私信",
        "线索成本": 717.686847856542,
        "线索数": 1660
      },
      "id": "recvenJ6Ykj23r",
      "record_id": "recvenJ6Ykj23r"
    },
    {
      "fields": {
        "名称": [
          {
            "text": "抖音直播-代播_2026-02",
            "type": "text"
          }
        ],
        "实际消费": 816731.044000437,
        "当前有效线索成本": 3347.25837705097,
        "月份": "2026-02",
        "有效线索": 244,
        "渠道": "抖音直播-代播",
        "线索成本": 1147.09416292196,
        "线索数": 712
      },
      "id": "recvenJ7eYKHX0",
      "record_id": "recvenJ7eYKHX0"
    },
    {
      "fields": {
        "名称": [
          {
            "text": "小红书品专_2026-02",
            "type": "text"
          }
        ],
        "实际消费": 16335.9,
        "当前有效线索成本": 710.25652173913,
        "月份": "2026-02",
        "有效线索": 23,
        "渠道": "小红书品专",
        "线索成本": 710.25652173913,
        "线索数": 23
      },
      "id": "recvenJ7xPkcXD",
      "record_id": "recvenJ7xPkcXD"
    },
    {
      "fields": {
        "名称": [
          {
            "text": "小红书直播_2026-02",
            "type": "text"
          }
        ],
        "实际消费": 151952.227272727,
        "当前有效线索成本": 2922.15821678322,
        "月份": "2026-02",
        "有效线索": 52,
        "渠道": "小红书直播",
        "线索成本": 1117.29578877005,
        "线索数": 136
      },
      "id": "recvenJ7QHiuw5",
      "record_id": "recvenJ7QHiuw5"
    },
    {
      "fields": {
        "名称": [
          {
            "text": "美团点评_2026-02",
            "type": "text"
          }
        ],
        "实际消费": 57519.47,
        "当前有效线索成本": 1983.43,
        "月份": "2026-02",
        "有效线索": 29,
        "渠道": "美团点评",
        "线索成本": 756.835131578947,
        "线索数": 76
      },
      "id": "recvenJ85r6ytL",
      "record_id": "recvenJ85r6ytL"
    },
    {
      "fields": {
        "名称": [
          {
            "text": "高德地图_2026-02",
            "type": "text"
          }
        ],
        "实际消费": 40079.76,
        "当前有效线索成本": 2003.988,
        "月份": "2026-02",
        "有效线索": 20,
        "渠道": "高德地图",
        "线索成本": 188.167887323944,
        "线索数": 213
      },
      "id": "recvenJ8qaQ40n",
      "record_id": "recvenJ8qaQ40n"
    },
    {
      "fields": {
        "名称": [
          {
            "text": "百度地图_2026-02",
            "type": "text"
          }
        ],
        "实际消费": 524.73,
        "当前有效线索成本": 131.1825,
        "月份": "2026-02",
        "有效线索": 4,
        "渠道": "百度地图",
        "线索成本": 29.1516666666667,
        "线索数": 18
      },
      "id": "recvenJ8HVoKv1",
      "record_id": "recvenJ8HVoKv1"
    },
    {
      "fields": {
        "名称": [
          {
            "text": "小红书_2026-03",
            "type": "text"
          }
        ],
        "实际消费": 1393696.89090909,
        "当前有效线索成本": 5688.55873840445,
        "月份": "2026-03",
        "有效线索": 245,
        "渠道": "小红书",
        "线索成本": 1946.50403758253,
        "线索数": 716
      },
      "id": "recveF0IQD6GxP",
      "record_id": "recveF0IQD6GxP"
    },
    {
      "fields": {
        "名称": [
          {
            "text": "朋友圈_2026-03",
            "type": "text"
          }
        ],
        "实际消费": 1970204.39800995,
        "当前有效线索成本": 3752.77028192372,
        "月份": "2026-03",
        "有效线索": 525,
        "渠道": "朋友圈",
        "线索成本": 811.45156425451,
        "线索数": 2428
      },
      "id": "recveF0JbzOKJU",
      "record_id": "recveF0JbzOKJU"
    },
    {
      "fields": {
        "名称": [
          {
            "text": "抖音私信_2026-03",
            "type": "text"
          }
        ],
        "实际消费": 2186985.61860465,
        "当前有效线索成本": 3877.63407554016,
        "月份": "2026-03",
        "有效线索": 564,
        "渠道": "抖音私信",
        "线索成本": 798.461343046605,
        "线索数": 2739
      },
      "id": "recveF0Jbz9Fe0",
      "record_id": "recveF0Jbz9Fe0"
    },
    {
      "fields": {
        "名称": [
          {
            "text": "抖音直播-代播_2026-03",
            "type": "text"
          }
        ],
        "实际消费": 2189421.8165957,
        "当前有效线索成本": 3606.95521679687,
        "月份": "2026-03",
        "有效线索": 607,
        "渠道": "抖音直播-代播",
        "线索成本": 1025.97086063529,
        "线索数": 2134
      },
      "id": "recveF0JbzKLAT",
      "record_id": "recveF0JbzKLAT"
    },
    {
      "fields": {
        "名称": [
          {
            "text": "小红书品专_2026-03",
            "type": "text"
          }
        ],
        "实际消费": 18086.175,
        "当前有效线索成本": 695.622115384615,
        "月份": "2026-03",
        "有效线索": 26,
        "渠道": "小红书品专",
        "线索成本": 695.622115384615,
        "线索数": 26
      },
      "id": "recveF0JbzecbJ",
      "record_id": "recveF0JbzecbJ"
    },
    {
      "fields": {
        "名称": [
          {
            "text": "小红书直播_2026-03",
            "type": "text"
          }
        ],
        "实际消费": 324759.890909091,
        "当前有效线索成本": 2752.20246533128,
        "月份": "2026-03",
        "有效线索": 118,
        "渠道": "小红书直播",
        "线索成本": 914.816594110115,
        "线索数": 355
      },
      "id": "recveF0JbzEvwV",
      "record_id": "recveF0JbzEvwV"
    },
    {
      "fields": {
        "名称": [
          {
            "text": "美团点评_2026-03",
            "type": "text"
          }
        ],
        "实际消费": 159376.18,
        "当前有效线索成本": 3887.22390243902,
        "月份": "2026-03",
        "有效线索": 41,
        "渠道": "美团点评",
        "线索成本": 905.546477272727,
        "线索数": 176
      },
      "id": "recveF0JbzlMRE",
      "record_id": "recveF0JbzlMRE"
    },
    {
      "fields": {
        "名称": [
          {
            "text": "高德地图_2026-03",
            "type": "text"
          }
        ],
        "实际消费": 66492.62,
        "当前有效线索成本": 1662.3155,
        "月份": "2026-03",
        "有效线索": 40,
        "渠道": "高德地图",
        "线索成本": 204.592676923077,
        "线索数": 325
      },
      "id": "recveF0Jbzhsmk",
      "record_id": "recveF0Jbzhsmk"
    },
    {
      "fields": {
        "名称": [
          {
            "text": "百度地图_2026-03",
            "type": "text"
          }
        ],
        "实际消费": 9144.02,
        "当前有效线索成本": 1524.00333333333,
        "月份": "2026-03",
        "有效线索": 6,
        "渠道": "百度地图",
        "线索成本": 145.143174603175,
        "线索数": 63
      },
      "id": "recveF0JbzeiPm",
      "record_id": "recveF0JbzeiPm"
    },
    {
      "fields": {
        "名称": [
          {
            "text": "小红书_2026-01",
            "type": "text"
          }
        ],
        "实际消费": 1158314.90909091,
        "当前有效线索成本": 4258.51069518717,
        "月份": "2026-01",
        "有效线索": 272,
        "渠道": "小红书",
        "线索成本": 2050.11488334674,
        "线索数": 565
      },
      "id": "recveF0Sk2QLky",
      "record_id": "recveF0Sk2QLky"
    },
    {
      "fields": {
        "名称": [
          {
            "text": "朋友圈_2026-01",
            "type": "text"
          }
        ],
        "实际消费": 1213404.72636816,
        "当前有效线索成本": 2587.21690057177,
        "月份": "2026-01",
        "有效线索": 469,
        "渠道": "朋友圈",
        "线索成本": 839.726454234021,
        "线索数": 1445
      },
      "id": "recveF0SHNn2pf",
      "record_id": "recveF0SHNn2pf"
    },
    {
      "fields": {
        "名称": [
          {
            "text": "抖音私信_2026-01",
            "type": "text"
          }
        ],
        "实际消费": 1594562.39069767,
        "当前有效线索成本": 2758.75846141466,
        "月份": "2026-01",
        "有效线索": 578,
        "渠道": "抖音私信",
        "线索成本": 804.521892380259,
        "线索数": 1982
      },
      "id": "recveF0SHN3yoF",
      "record_id": "recveF0SHN3yoF"
    },
    {
      "fields": {
        "名称": [
          {
            "text": "抖音直播-代播_2026-01",
            "type": "text"
          }
        ],
        "实际消费": 1796214.77913812,
        "当前有效线索成本": 3742.11412320443,
        "月份": "2026-01",
        "有效线索": 480,
        "渠道": "抖音直播-代播",
        "线索成本": 1391.33600243077,
        "线索数": 1291
      },
      "id": "recveF0SHNms9V",
      "record_id": "recveF0SHNms9V"
    },
    {
      "fields": {
        "名称": [
          {
            "text": "小红书品专_2026-01",
            "type": "text"
          }
        ],
        "实际消费": 17960.695,
        "当前有效线索成本": 561.27171875,
        "月份": "2026-01",
        "有效线索": 32,
        "渠道": "小红书品专",
        "线索成本": 561.27171875,
        "线索数": 32
      },
      "id": "recveF0SHNnnJl",
      "record_id": "recveF0SHNnnJl"
    },
    {
      "fields": {
        "名称": [
          {
            "text": "小红书直播_2026-01",
            "type": "text"
          }
        ],
        "实际消费": 298047.090909091,
        "当前有效线索成本": 3041.29684601113,
        "月份": "2026-01",
        "有效线索": 98,
        "渠道": "小红书直播",
        "线索成本": 1159.71630703926,
        "线索数": 257
      },
      "id": "recveF0SHN69K1",
      "record_id": "recveF0SHN69K1"
    },
    {
      "fields": {
        "名称": [
          {
            "text": "美团点评_2026-01",
            "type": "text"
          }
        ],
        "实际消费": 132859.03,
        "当前有效线索成本": 2657.1806,
        "月份": "2026-01",
        "有效线索": 50,
        "渠道": "美团点评",
        "线索成本": 948.993071428571,
        "线索数": 140
      },
      "id": "recveF0SHNeB9d",
      "record_id": "recveF0SHNeB9d"
    },
    {
      "fields": {
        "名称": [
          {
            "text": "高德地图_2026-01",
            "type": "text"
          }
        ],
        "实际消费": 55562.88,
        "当前有效线索成本": 1736.34,
        "月份": "2026-01",
        "有效线索": 32,
        "渠道": "高德地图",
        "线索成本": 171.49037037037,
        "线索数": 324
      },
      "id": "recveF0SHNiqz4",
      "record_id": "recveF0SHNiqz4"
    },
    {
      "fields": {
        "名称": [
          {
            "text": "百度地图_2026-01",
            "type": "text"
          }
        ],
        "实际消费": 0,
        "当前有效线索成本": 0,
        "月份": "2026-01",
        "有效线索": 4,
        "渠道": "百度地图",
        "线索成本": 0,
        "线索数": 18
      },
      "id": "recveF0SHN9j3O",
      "record_id": "recveF0SHN9j3O"
    },
    {
      "fields": {
        "名称": [
          {
            "text": "视频号直播_2026-03",
            "type": "text"
          }
        ],
        "实际消费": 7628.19900497513,
        "当前有效线索成本": null,
        "月份": "2026-03",
        "有效线索": 0,
        "渠道": "视频号直播",
        "线索成本": null,
        "线索数": 0
      },
      "id": "recveRwtbfX6tM",
      "record_id": "recveRwtbfX6tM"
    },
    {
      "fields": {
        "名称": [
          {
            "text": "小红书_2026-04",
            "type": "text"
          }
        ],
        "实际消费": 691695.681818182,
        "当前有效线索成本": null,
        "月份": "2026-04",
        "有效线索": 0,
        "渠道": "小红书",
        "线索成本": null,
        "线索数": 0
      },
      "id": "recvf3Om5ydCDZ",
      "record_id": "recvf3Om5ydCDZ"
    },
    {
      "fields": {
        "名称": [
          {
            "text": "朋友圈_2026-04",
            "type": "text"
          }
        ],
        "实际消费": 1075655.07462687,
        "当前有效线索成本": null,
        "月份": "2026-04",
        "有效线索": 0,
        "渠道": "朋友圈",
        "线索成本": 861.213030125593,
        "线索数": 1249
      },
      "id": "recvgKKBQpwyRB",
      "record_id": "recvgKKBQpwyRB"
    },
    {
      "fields": {
        "名称": [
          {
            "text": "抖音私信_2026-04",
            "type": "text"
          }
        ],
        "实际消费": 745026.809302326,
        "当前有效线索成本": null,
        "月份": "2026-04",
        "有效线索": 0,
        "渠道": "抖音私信",
        "线索成本": null,
        "线索数": 0
      },
      "id": "recvgKKG8vIbka",
      "record_id": "recvgKKG8vIbka"
    },
    {
      "fields": {
        "名称": [
          {
            "text": "抖音直播-代播_2026-04",
            "type": "text"
          }
        ],
        "实际消费": 995065.207347964,
        "当前有效线索成本": 5237.18530183139,
        "月份": "2026-04",
        "有效线索": 190,
        "渠道": "抖音直播-代播",
        "线索成本": 1401.50029203939,
        "线索数": 710
      },
      "id": "recvgKKG8vSUXk",
      "record_id": "recvgKKG8vSUXk"
    },
    {
      "fields": {
        "名称": [
          {
            "text": "小红书品专_2026-04",
            "type": "text"
          }
        ],
        "实际消费": 17502.75,
        "当前有效线索成本": null,
        "月份": "2026-04",
        "有效线索": 0,
        "渠道": "小红书品专",
        "线索成本": null,
        "线索数": 0
      },
      "id": "recvgKKG8v1Ahd",
      "record_id": "recvgKKG8v1Ahd"
    },
    {
      "fields": {
        "名称": [
          {
            "text": "小红书直播_2026-04",
            "type": "text"
          }
        ],
        "实际消费": 207524.172727273,
        "当前有效线索成本": 3640.77496012759,
        "月份": "2026-04",
        "有效线索": 57,
        "渠道": "小红书直播",
        "线索成本": 974.291890738369,
        "线索数": 213
      },
      "id": "recvgKKG8vx5B2",
      "record_id": "recvgKKG8vx5B2"
    },
    {
      "fields": {
        "名称": [
          {
            "text": "美团点评_2026-04",
            "type": "text"
          }
        ],
        "实际消费": 79466.03,
        "当前有效线索成本": null,
        "月份": "2026-04",
        "有效线索": 0,
        "渠道": "美团点评",
        "线索成本": null,
        "线索数": 0
      },
      "id": "recvgKKG8v4Zpq",
      "record_id": "recvgKKG8v4Zpq"
    },
    {
      "fields": {
        "名称": [
          {
            "text": "高德地图_2026-04",
            "type": "text"
          }
        ],
        "实际消费": 53553.53,
        "当前有效线索成本": null,
        "月份": "2026-04",
        "有效线索": 0,
        "渠道": "高德地图",
        "线索成本": null,
        "线索数": 0
      },
      "id": "recvgKKG8vI6pG",
      "record_id": "recvgKKG8vI6pG"
    },
    {
      "fields": {
        "名称": [
          {
            "text": "百度地图_2026-04",
            "type": "text"
          }
        ],
        "实际消费": 3089.14,
        "当前有效线索成本": null,
        "月份": "2026-04",
        "有效线索": 0,
        "渠道": "百度地图",
        "线索成本": null,
        "线索数": 0
      },
      "id": "recvgKKG8vwYtJ",
      "record_id": "recvgKKG8vwYtJ"
    },
    {
      "fields": {
        "名称": [
          {
            "text": "视频号直播_2026-04",
            "type": "text"
          }
        ],
        "实际消费": 168912.397114428,
        "当前有效线索成本": null,
        "月份": "2026-04",
        "有效线索": 0,
        "渠道": "视频号直播",
        "线索成本": null,
        "线索数": 0
      },
      "id": "recvgKKG8vTKMR",
      "record_id": "recvgKKG8vTKMR"
    }
  ],
  "total": 38
}